nanonis_control/__init__.py
nanonis_control/nanonis_tcp.py
nanonis_control-1.0.1.dist-info/LICENSE
nanonis_control-1.0.1.dist-info/METADATA
nanonis_control-1.0.1.dist-info/WHEEL
nanonis_control-1.0.1.dist-info/top_level.txt
nanonis_control-1.0.1.dist-info/RECORD
