Metadata-Version: 2.1
Name: nanonis-control
Version: 1.0.1
Summary: Control Nanonis with Python instead of LabView!
Home-page: https://github.com/dilwong/nanonis_control
Author: Dillon Wong
Author-email: 
License-File: LICENSE
